Metadata-Version: 2.1
Name: legendador
Version: 0.0.3
Summary: Legendador de videos para o portugues ou esperanto
Home-page: 
Author: PCO, Bombark
Author-email: coltecpco@skiff.org
Classifier: Programming Language :: Python :: 3
Classifier: Programming Language :: Python :: 3.7
Classifier: Programming Language :: Python :: 3.8
Classifier: License :: OSI Approved :: MIT License
Requires-Python: >=3
Requires-Dist: pathlib
Requires-Dist: click
Requires-Dist: opencv-python
Requires-Dist: ffmpeg-python
Requires-Dist: googletrans==4.0.0-rc1
Requires-Dist: numpy
Requires-Dist: sh
